djangocms_page_tags/__init__.py
djangocms_page_tags/admin.py
djangocms_page_tags/cms_toolbars.py
djangocms_page_tags/models.py
djangocms_page_tags/utils.py
djangocms_page_tags/locale/ar/LC_MESSAGES/django.mo
djangocms_page_tags/locale/ar/LC_MESSAGES/django.po
djangocms_page_tags/locale/de/LC_MESSAGES/django.mo
djangocms_page_tags/locale/de/LC_MESSAGES/django.po
djangocms_page_tags/locale/en/LC_MESSAGES/django.mo
djangocms_page_tags/locale/en/LC_MESSAGES/django.po
djangocms_page_tags/locale/es/LC_MESSAGES/django.mo
djangocms_page_tags/locale/es/LC_MESSAGES/django.po
djangocms_page_tags/locale/it/LC_MESSAGES/django.mo
djangocms_page_tags/locale/it/LC_MESSAGES/django.po
djangocms_page_tags/locale/lt/LC_MESSAGES/django.mo
djangocms_page_tags/locale/lt/LC_MESSAGES/django.po
djangocms_page_tags/locale/pt_BR/LC_MESSAGES/django.mo
djangocms_page_tags/locale/pt_BR/LC_MESSAGES/django.po
djangocms_page_tags/locale/ru/LC_MESSAGES/django.mo
djangocms_page_tags/locale/ru/LC_MESSAGES/django.po
djangocms_page_tags/locale/tr/LC_MESSAGES/django.mo
djangocms_page_tags/locale/tr/LC_MESSAGES/django.po
djangocms_page_tags/migrations/0001_initial.py
djangocms_page_tags/migrations/__init__.py
djangocms_page_tags/static/djangocms_page_tags/css/djangocms_page_tags_admin.css
djangocms_page_tags/templates/djangocms_page_tags/base.html
djangocms_page_tags/templates/djangocms_page_tags/templatetags/page_tags.html
djangocms_page_tags/templates/djangocms_page_tags/templatetags/title_tags.html
djangocms_page_tags/templatetags/__init__.py
djangocms_page_tags/templatetags/page_tags.py
djangocms_page_tags-1.2.0.dist-info/LICENSE
djangocms_page_tags-1.2.0.dist-info/METADATA
djangocms_page_tags-1.2.0.dist-info/WHEEL
djangocms_page_tags-1.2.0.dist-info/top_level.txt
djangocms_page_tags-1.2.0.dist-info/RECORD
