Metadata-Version: 2.2
Name: djangocms-page-tags
Version: 1.2.0
Summary: Tagged pages for django CMS 3
Home-page: https://github.com/nephila/djangocms-page-tags
Author: Iacopo Spalletti
Author-email: i.spalletti@nephila.digital
License: BSD
Project-URL: Documentation, https://djangocms-page-tags.readthedocs.io/
Keywords: djangocms-page-tags
Classifier: Development Status :: 5 - Production/Stable
Classifier: Framework :: Django
Classifier: Intended Audience :: Developers
Classifier: License :: OSI Approved :: BSD License
Classifier: Natural Language :: English
Classifier: Framework :: Django
Classifier: Framework :: Django :: 4.2
Classifier: Programming Language :: Python :: 3
Classifier: Programming Language :: Python :: 3.10
Classifier: Programming Language :: Python :: 3.11
Requires-Python: >=3.10
License-File: LICENSE
Requires-Dist: django-cms>=3.11
Requires-Dist: django-taggit>=0.11.2
Requires-Dist: django-taggit-autosuggest
Requires-Dist: django-classy-tags>=0.3.4.1
Provides-Extra: docs
Requires-Dist: django<5.0; extra == "docs"
